science_ocr/__init__.py
science_ocr/engine.py
science_ocr/pdf2image.py
science_ocr/pipeline.py
science_ocr-0.3.0.dist-info/METADATA
science_ocr-0.3.0.dist-info/WHEEL
science_ocr-0.3.0.dist-info/licenses/LICENSE
science_ocr-0.3.0.dist-info/RECORD
