Metadata-Version: 2.4
Name: science-ocr
Version: 0.3.0
Summary: Extract clean, structured text from scientific papers in PDF format
License: GPL-3.0-or-later
License-File: LICENSE
Keywords: ocr,pdf,scientific-papers,text-extraction,document-processing,research-papers
Author: Tomás Golomb Durán
Author-email: tomasgduran@gmail.com
Maintainer: Tomás Golomb Durán
Maintainer-email: tomasgduran@gmail.com
Requires-Python: >=3.10,<4.0
Classifier: Development Status :: 4 - Beta
Classifier: Intended Audience :: Science/Research
Classifier: Intended Audience :: Developers
Classifier: License :: OSI Approved :: GNU General Public License v3 or later (GPLv3+)
Classifier: Programming Language :: Python :: 3
Classifier: Programming Language :: Python :: 3.8
Classifier: Programming Language :: Python :: 3.9
Classifier: Programming Language :: Python :: 3.10
Classifier: Programming Language :: Python :: 3.11
Classifier: Programming Language :: Python :: 3.12
Classifier: Topic :: Scientific/Engineering
Classifier: Topic :: Text Processing
Classifier: Operating System :: OS Independent
Requires-Dist: pymupdf (>=1.26.6,<2.0.0)
Requires-Dist: surya-ocr (>=0.17.0,<0.18.0)
Project-URL: Homepage, https://github.com/ToGo347/science-ocr
